[
    {
        "Tanggal": "13 Jun 2024",
        "Jam": "00:01:23 WIB",
        "DateTime": "2024-06-12T17:01:23+00:00",
        "Coordinates": "4.36,126.65",
        "Lintang": "4.36 LU",
        "Bujur": "126.65 BT",
        "Magnitude": "6.0",
        "Kedalaman": "30 km",
        "Wilayah": "Pusat gempa berada di laut 40 km barat laut Melonguane",
        "Dirasakan": "III Kepulauan Sangihe, III-IV Kepulauan Talaud, II Manado"
    },
    {
        "Tanggal": "11 Jun 2024",
        "Jam": "15:07:20 WIB",
        "DateTime": "2024-06-11T08:07:20+00:00",
        "Coordinates": "0.89,97.76",
        "Lintang": "0.89 LU",
        "Bujur": "97.76 BT",
        "Magnitude": "4.5",
        "Kedalaman": "31 km",
        "Wilayah": "Pusat gempa berada di darat 27 km tenggara Nias",
        "Dirasakan": "II-III Gunungsitoli, II-III Kab. Nias, II-III Kab. Nias Selatan"
    },
    {
        "Tanggal": "11 Jun 2024",
        "Jam": "06:46:10 WIB",
        "DateTime": "2024-06-10T23:46:10+00:00",
        "Coordinates": "4.72,95.88",
        "Lintang": "4.72 LU",
        "Bujur": "95.88 BT",
        "Magnitude": "4.6",
        "Kedalaman": "79 km",
        "Wilayah": "Pusat gempa berada di darat 34 km timur laut Calang - Aceh Jaya",
        "Dirasakan": "II-III Lamno"
    },
    {
        "Tanggal": "11 Jun 2024",
        "Jam": "00:29:36 WIB",
        "DateTime": "2024-06-10T17:29:36+00:00",
        "Coordinates": "-6.77,112.06",
        "Lintang": "6.77 LS",
        "Bujur": "112.06 BT",
        "Magnitude": "3.2",
        "Kedalaman": "9 km",
        "Wilayah": "Pusat gempa berada di laut 14 km timur laut Tuban",
        "Dirasakan": "II Tuban"
    },
    {
        "Tanggal": "10 Jun 2024",
        "Jam": "20:30:14 WIB",
        "DateTime": "2024-06-10T13:30:14+00:00",
        "Coordinates": "-2.46,120.78",
        "Lintang": "2.46 LS",
        "Bujur": "120.78 BT",
        "Magnitude": "2.6",
        "Kedalaman": "5 km",
        "Wilayah": "Pusat gempa berada di darat 45 km baratlaut Luwu Timur",
        "Dirasakan": "II Mangkutana"
    },
    {
        "Tanggal": "10 Jun 2024",
        "Jam": "14:08:03 WIB",
        "DateTime": "2024-06-10T07:08:03+00:00",
        "Coordinates": "5.56,95.43",
        "Lintang": "5.56 LU",
        "Bujur": "95.43 BT",
        "Magnitude": "3.5",
        "Kedalaman": "2 km",
        "Wilayah": "Pusat gempa berada di darat 39 km tenggara Kota Sabang",
        "Dirasakan": "II-III Aceh Besar"
    },
    {
        "Tanggal": "10 Jun 2024",
        "Jam": "13:02:05 WIB",
        "DateTime": "2024-06-10T06:02:05+00:00",
        "Coordinates": "0.17,124.90",
        "Lintang": "0.17 LU",
        "Bujur": "124.90 BT",
        "Magnitude": "4.8",
        "Kedalaman": "15 km",
        "Wilayah": "Pusat gempa berada di laut 72 km tenggara Tutuyan - Bolaang Mongondow Timur",
        "Dirasakan": "II Minahasa"
    },
    {
        "Tanggal": "10 Jun 2024",
        "Jam": "10:35:35 WIB",
        "DateTime": "2024-06-10T03:35:35+00:00",
        "Coordinates": "-2.78,122.14",
        "Lintang": "2.78 LS",
        "Bujur": "122.14 BT",
        "Magnitude": "3.8",
        "Kedalaman": "5 km",
        "Wilayah": "Pusat gempa berada di laut 27 km tenggara Morowali",
        "Dirasakan": "III Bahodopi"
    },
    {
        "Tanggal": "10 Jun 2024",
        "Jam": "05:54:54 WIB",
        "DateTime": "2024-06-09T22:54:54+00:00",
        "Coordinates": "-0.45,100.25",
        "Lintang": "0.45 LS",
        "Bujur": "100.25 BT",
        "Magnitude": "4.0",
        "Kedalaman": "10 km",
        "Wilayah": "Pusat gempa berada di darat 15 km barat laut Padang Panjang",
        "Dirasakan": "III Padang Panjang, II - III Bukittinggi, II - III Padang Pariaman, II - III Agam"
    },
    {
        "Tanggal": "09 Jun 2024",
        "Jam": "00:01:56 WIB",
        "DateTime": "2024-06-08T17:01:56+00:00",
        "Coordinates": "-8.12,107.87",
        "Lintang": "8.12 LS",
        "Bujur": "107.87 BT",
        "Magnitude": "4.2",
        "Kedalaman": "43 km",
        "Wilayah": "Pusat gempa berada di laut 82 km BaratDaya Kab. Pangandaran",
        "Dirasakan": "II - III Pangandaran, II - III Garut"
    },
    {
        "Tanggal": "08 Jun 2024",
        "Jam": "05:44:12 WIB",
        "DateTime": "2024-06-07T22:44:12+00:00",
        "Coordinates": "3.02,97.41",
        "Lintang": "3.02 LU",
        "Bujur": "97.41 BT",
        "Magnitude": "3.9",
        "Kedalaman": "4 km",
        "Wilayah": "Pusat gempa berada di darat 35 km tenggara Kab. Aceh Selatan",
        "Dirasakan": "III Aceh Selatan"
    },
    {
        "Tanggal": "07 Jun 2024",
        "Jam": "23:31:06 WIB",
        "DateTime": "2024-06-07T16:31:06+00:00",
        "Coordinates": "-2.86,139.37",
        "Lintang": "2.86 LS",
        "Bujur": "139.37 BT",
        "Magnitude": "5.8",
        "Kedalaman": "45 km",
        "Wilayah": "Pusat gempa berada di darat 95 km timur laut Kobagma",
        "Dirasakan": "III Kab. Jayapura"
    },
    {
        "Tanggal": "07 Jun 2024",
        "Jam": "07:46:50 WIB",
        "DateTime": "2024-06-07T00:46:50+00:00",
        "Coordinates": "-3.43,128.13",
        "Lintang": "3.43 LS",
        "Bujur": "128.13 BT",
        "Magnitude": "4.6",
        "Kedalaman": "69 km",
        "Wilayah": "Pusat gempa berada di laut 27 km barat Kairatu",
        "Dirasakan": "II Ambon"
    },
    {
        "Tanggal": "07 Jun 2024",
        "Jam": "02:57:52 WIB",
        "DateTime": "2024-06-06T19:57:52+00:00",
        "Coordinates": "-7.79,107.29",
        "Lintang": "7.79 LS",
        "Bujur": "107.29 BT",
        "Magnitude": "4.2",
        "Kedalaman": "24 km",
        "Wilayah": "Pusat gempa berada di laut 89 km BaratDaya Kab Bandung",
        "Dirasakan": "II Garut, II Cianjur, II Tasikmalaya, II GunungHalu"
    },
    {
        "Tanggal": "06 Jun 2024",
        "Jam": "20:40:29 WIB",
        "DateTime": "2024-06-06T13:40:29+00:00",
        "Coordinates": "-1.43,133.91",
        "Lintang": "1.43 LS",
        "Bujur": "133.91 BT",
        "Magnitude": "3.2",
        "Kedalaman": "35 km",
        "Wilayah": "Pusat gempa berada di darat 17 km barat daya Pegunungan Arfak",
        "Dirasakan": "II Manokwari Selatan"
    },
    {
        "Tanggal": "06 Jun 2024",
        "Jam": "20:15:40 WIB",
        "DateTime": "2024-06-06T13:15:40+00:00",
        "Coordinates": "-9.22,116.94",
        "Lintang": "9.22 LS",
        "Bujur": "116.94 BT",
        "Magnitude": "5.1",
        "Kedalaman": "10 km",
        "Wilayah": "Pusat gempa berada di laut 52 km Tenggara Sumbawa Barat",
        "Dirasakan": "III Gianyar, III Badung, III Denpasar, III Sumbawa Barat, III Sumbawa, III Lombok Tengah, III Lombok Barat, III Mataram, III Lombok Timur, III Lombok Utara, III Dompu"
    },
    {
        "Tanggal": "06 Jun 2024",
        "Jam": "19:46:26 WIB",
        "DateTime": "2024-06-06T12:46:26+00:00",
        "Coordinates": "-1.15,119.80",
        "Lintang": "1.15 LS",
        "Bujur": "119.80 BT",
        "Magnitude": "3.8",
        "Kedalaman": "34 km",
        "Wilayah": "Pusat gempa berada di darat 29 km Selatan Palu",
        "Dirasakan": "II Sigi"
    },
    {
        "Tanggal": "06 Jun 2024",
        "Jam": "02:21:11 WIB",
        "DateTime": "2024-06-05T19:21:11+00:00",
        "Coordinates": "-6.82,107.93",
        "Lintang": "6.82 LS",
        "Bujur": "107.93 BT",
        "Magnitude": "2.7",
        "Kedalaman": "9 km",
        "Wilayah": "Pusat gempa berada di darat 4 km timur laut Kab. Sumedang",
        "Dirasakan": "II Sumedang Selatan, II Cimalaka"
    },
    {
        "Tanggal": "05 Jun 2024",
        "Jam": "18:16:14 WIB",
        "DateTime": "2024-06-05T11:16:14+00:00",
        "Coordinates": "0.42,98.50",
        "Lintang": "0.42 LU",
        "Bujur": "98.50 BT",
        "Magnitude": "5.7",
        "Kedalaman": "57 km",
        "Wilayah": "Pusat gempa berada di laut 78 Km tenggara Nias Selatan",
        "Dirasakan": "III Nias Selatan, II Gunung Sitoli, III Pasaman Barat, III Padang Pariaman, III Agam, II Padang Panjang, III Padang Sidempuan, III Tapanuli Utara"
    },
    {
        "Tanggal": "05 Jun 2024",
        "Jam": "13:30:20 WIB",
        "DateTime": "2024-06-05T06:30:20+00:00",
        "Coordinates": "-8.23,118.00",
        "Lintang": "8.23 LS",
        "Bujur": "118.00 BT",
        "Magnitude": "4.7",
        "Kedalaman": "214 km",
        "Wilayah": "Pusat gempa berada di darat 61 Km barat laut Dompu",
        "Dirasakan": "II Sumbawa"
    }
]